officetools/__init__.py
officetools/_version.py
officetools/kpi.py
officetools-0.0.2.dist-info/LICENSE
officetools-0.0.2.dist-info/METADATA
officetools-0.0.2.dist-info/WHEEL
officetools-0.0.2.dist-info/top_level.txt
officetools-0.0.2.dist-info/RECORD
