Metadata-Version: 2.1
Name: officetools
Version: 0.0.2
Summary: Forecasting package for office automation
Home-page: https://github.com/yForecasting/officetools
Author: Yves R. Sagaert
Author-email: yves.r.sagaert@gmail.com
License: GNU GPLv3
Classifier: Development Status :: 4 - Beta
Classifier: License :: OSI Approved :: GNU General Public License v3 (GPLv3)
Classifier: Programming Language :: Python
Classifier: Topic :: Software Development :: Libraries
Classifier: Topic :: Software Development :: Libraries :: Python Modules
Classifier: Intended Audience :: Developers
Requires-Python: >=3.5
License-File: LICENSE
Requires-Dist: pandas
Requires-Dist: matplotlib
Requires-Dist: numpy
